sedpack-0.1.4.dist-info/METADATA
sedpack-0.1.4.dist-info/WHEEL
sedpack-0.1.4.dist-info/licenses/LICENSE
sedpack.libs/libgcc_s-27e5a392.so.1
sedpack/__init__.py
sedpack/_sedpack_rs.cpython-311-i386-linux-musl.so
sedpack/io/__init__.py
sedpack/io/compress.py
sedpack/io/dataset.py
sedpack/io/dataset_base.py
sedpack/io/dataset_filler.py
sedpack/io/dataset_iteration.py
sedpack/io/dataset_writing.py
sedpack/io/errors.py
sedpack/io/file_info.py
sedpack/io/flatbuffer/__init__.py
sedpack/io/flatbuffer/iterate.py
sedpack/io/flatbuffer/shard.fbs
sedpack/io/flatbuffer/shardfile/Attribute.py
sedpack/io/flatbuffer/shardfile/Example.py
sedpack/io/flatbuffer/shardfile/Shard.py
sedpack/io/flatbuffer/shardfile/__init__.py
sedpack/io/flatbuffer/unit_tests/shard_writer_flatbuffer_test_schema.fbs
sedpack/io/flatbuffer/unit_tests/shard_writer_flatbuffer_test_schema/NumPyVectorTest.py
sedpack/io/flatbuffer/unit_tests/shard_writer_flatbuffer_test_schema/__init__.py
sedpack/io/iteration/__init__.py
sedpack/io/iteration/rust_batched_generator.py
sedpack/io/iteration/rust_generator.py
sedpack/io/itertools/__init__.py
sedpack/io/itertools/itertools.py
sedpack/io/itertools/lazy_pool.py
sedpack/io/merge_shard_infos.py
sedpack/io/metadata.py
sedpack/io/npz/__init__.py
sedpack/io/npz/iterate_npz.py
sedpack/io/shard/__init__.py
sedpack/io/shard/get_shard_writer.py
sedpack/io/shard/iterate_shard_base.py
sedpack/io/shard/shard.py
sedpack/io/shard/shard_writer_base.py
sedpack/io/shard/shard_writer_flatbuffer.py
sedpack/io/shard/shard_writer_np.py
sedpack/io/shard/shard_writer_tfrec.py
sedpack/io/shard_file_metadata.py
sedpack/io/shard_info_iterator/__init__.py
sedpack/io/shard_info_iterator/cached_shard_info_iterator.py
sedpack/io/shard_info_iterator/shard_info_iterator.py
sedpack/io/tfrec/__init__.py
sedpack/io/tfrec/read.py
sedpack/io/tfrec/tfdata.py
sedpack/io/types.py
sedpack/io/utils.py
sedpack/py.typed
sedpack-0.1.4.dist-info/RECORD
