Metadata-Version: 2.4
Name: sedpack
Version: 0.1.4
Classifier: Development Status :: 5 - Production/Stable
Classifier: Environment :: Console
Classifier: Framework :: Jupyter
Classifier: License :: OSI Approved :: Apache Software License
Classifier: Intended Audience :: Science/Research
Classifier: Programming Language :: Python :: 3
Classifier: Topic :: Scientific/Engineering :: Artificial Intelligence
Requires-Dist: aiofiles
Requires-Dist: asyncstdlib
Requires-Dist: flatbuffers
Requires-Dist: lz4
Requires-Dist: numpy
Requires-Dist: pydantic
Requires-Dist: semver
Requires-Dist: tenacity
Requires-Dist: tensorflow
Requires-Dist: tqdm
Requires-Dist: xxhash
Requires-Dist: zstandard
Requires-Dist: maturin[patchelf,zig] ; platform_system != 'Windows' and extra == 'dev'
Requires-Dist: maturin[zig] ; platform_system == 'Windows' and extra == 'dev'
Requires-Dist: mypy ; extra == 'dev'
Requires-Dist: pylint ; extra == 'dev'
Requires-Dist: pytest ; extra == 'dev'
Requires-Dist: pytest-asyncio ; extra == 'dev'
Requires-Dist: pytest-cov ; extra == 'dev'
Requires-Dist: types-aiofiles ; extra == 'dev'
Requires-Dist: types-tensorflow ; extra == 'dev'
Requires-Dist: types-tqdm ; extra == 'dev'
Requires-Dist: yapf ; extra == 'dev'
Provides-Extra: dev
License-File: LICENSE
Summary: General ML dataset package
Keywords: machine learning,dataset
Author: Elie Bursztein, Karel Král, Jean-Michel Picod
License: Apache License 2.0
Requires-Python: >=3.10
Project-URL: Homepage, https://github.com/google/sedpack
Project-URL: Bug Tracker, https://github.com/google/sedpack
